README.md
setup.cfg
setup.py
digital_unit/Area.py
digital_unit/Lenth.py
digital_unit/Temperature.py
digital_unit/Volume.py
digital_unit/__init__.py
digital_unit/root.py
digital_unit/sample.py
digital_unit/volume.py
digital_unit.egg-info/PKG-INFO
digital_unit.egg-info/SOURCES.txt
digital_unit.egg-info/dependency_links.txt
digital_unit.egg-info/top_level.txt