Metadata-Version: 2.1
Name: digital-unit
Version: 1.6.0
Summary: number and units
Author: st201109
Author-email: st20110913@outlook.com
License: MIT
Keywords: SOME,MEANINGFULL,MATH
Classifier: Programming Language :: Python :: 3.6
